<?xml version="1.0" encoding="UTF-8" standalone="no"?>
<!-- Generated 6 nov. 2017 22:46:44 by Hibernate Tools 5.2.3.Final --><!DOCTYPE hibernate-mapping PUBLIC "-//Hibernate/Hibernate Mapping DTD 3.0//EN" "http://www.hibernate.org/dtd/hibernate-mapping-3.0.dtd">
<hibernate-mapping auto-import="true" default-access="property" default-cascade="none" default-lazy="true">
    <class catalog="pdg" dynamic-insert="false" dynamic-update="false" mutable="true" name="Tournament" optimistic-lock="version" polymorphism="implicit" select-before-update="false" table="tournament">
        <id name="id" type="java.lang.Integer">
            <column name="ID"/>
            <generator class="identity"/>
        </id>
        <property generated="never" lazy="false" name="title" optimistic-lock="true" type="string" unique="false">
            <column length="45" name="title" not-null="true"/>
        </property>
        <property generated="never" lazy="false" name="created" optimistic-lock="true" type="timestamp" unique="false">
            <column length="19" name="created" not-null="true"/>
        </property>
        <set embed-xml="true" fetch="select" inverse="true" lazy="true" mutable="true" name="chats" optimistic-lock="true" sort="unsorted" table="chat">
            <key on-delete="noaction">
                <column name="tournament"/>
            </key>
            <one-to-many class="Chat" embed-xml="true" not-found="exception"/>
        </set>
        <set embed-xml="true" fetch="select" inverse="true" lazy="true" mutable="true" name="matchlists" optimistic-lock="true" sort="unsorted" table="matchlist">
            <key on-delete="noaction">
                <column name="TournamentID" not-null="true"/>
            </key>
            <one-to-many class="Matchlist" embed-xml="true" not-found="exception"/>
        </set>
        <set embed-xml="true" fetch="select" inverse="true" lazy="true" mutable="true" name="games" optimistic-lock="true" sort="unsorted" table="game">
            <key on-delete="noaction">
                <column name="tournament"/>
            </key>
            <one-to-many class="Game" embed-xml="true" not-found="exception"/>
        </set>
    </class>
</hibernate-mapping>
